LWE4.py
LWE4-0.0.0.2.dist-info/LICENSE
LWE4-0.0.0.2.dist-info/METADATA
LWE4-0.0.0.2.dist-info/WHEEL
LWE4-0.0.0.2.dist-info/top_level.txt
LWE4-0.0.0.2.dist-info/RECORD
