Metadata-Version: 2.1
Name: LWE4
Version: 0.0.0.2
Summary: A Lattice based Asymetric public-key encryption algorithm based on learning with errors problem.
Home-page: https://github.com/ApratimR/learning_with_errors
Author: Apratim Ray
Author-email: apratimr55@gmail.com
Classifier: Programming Language :: Python :: 3
Classifier: License :: OSI Approved :: Apache Software License
Classifier: Operating System :: OS Independent
Requires-Python: >=3.6
License-File: LICENSE
